SCATPY.cp38-win_amd64.pyd
SCATPY.pyd
pySCATMECH/__init__.py
pySCATMECH/brdf.py
pySCATMECH/crossrcw.py
pySCATMECH/fresnel.py
pySCATMECH/integrate.py
pySCATMECH/local.py
pySCATMECH/model.py
pySCATMECH/mueller.py
pySCATMECH/rcw.py
pySCATMECH/scatterer.py
pySCATMECH-0.1.9.dist-info/LICENSE
pySCATMECH-0.1.9.dist-info/METADATA
pySCATMECH-0.1.9.dist-info/WHEEL
pySCATMECH-0.1.9.dist-info/top_level.txt
pySCATMECH-0.1.9.dist-info/RECORD
