Metadata-Version: 2.1
Name: pySCATMECH
Version: 0.1.9
Summary: A Python interface to the SCATMECH library
Home-page: https://github.com/thomas-germer/pyscatmech
Author: Thomas A. Germer
Author-email: thomas.germer@nist.gov
License: UNKNOWN
Platform: UNKNOWN
Classifier: Programming Language :: Python :: 3
Classifier: Development Status :: 4 - Beta
Classifier: Intended Audience :: Science/Research
Classifier: License :: Public Domain
Classifier: Topic :: Scientific/Engineering :: Physics
Classifier: Operating System :: Microsoft :: Windows
Requires-Python: >=3.6
License-File: LICENSE
